{
  "Бонусы": {
    "Бонус 5$": "Вам начислен бонус 5$. 🎉",
    "Бонус 10$": "Вам начислен бонус 10$.",
    "VIP Bonus": "VIP активирован ⭐",
    "Cashback": "Доступен cashback"
    "Cashback": "Доступен cashback1"
  },

  "Верификация": {
    "ID": "Отправьте документ.",
    "Selfie": "Нужно selfie с документом.",
    "Адрес": "Подтвердите адрес документом."
  },

  "Приветствие": {
    "RU": "Здравствуйте! Чем могу помочь?",
    "EN": "Hello! How can I help you?",
    "VIP": "Welcome back VIP ⭐"
  },

  "Hold": {
    "2 min": "Please wait 2 minutes.",
    "5 min": "Please wait 5 minutes.",
    "Transfer": "Transferring to specialist..."
  }
}
